pydisort/__init__.py
pydisort/py.typed
pydisort/pydisort.cpython-311-x86_64-linux-gnu.so
pydisort/pydisort.pyi
pydisort/cdisort213/CMakeLists.txt
pydisort/cdisort213/COPYING
pydisort/cdisort213/DISORT2.doc
pydisort/cdisort213/HOWTO_cdisort
pydisort/cdisort213/Makefile_cdisort
pydisort/cdisort213/README_cdisort
pydisort/cdisort213/cdisort.c
pydisort/cdisort213/cdisort.h
pydisort/cdisort213/locate.c
pydisort/cdisort213/locate.h
pydisort/disort/CMakeLists.txt
pydisort/disort/add_arg.h
pydisort/disort/disort.cpp
pydisort/disort/disort.hpp
pydisort/disort/disort_dispatch.cpp
pydisort/disort/disort_dispatch.cu
pydisort/disort/disort_dispatch.hpp
pydisort/disort/disort_formatter.hpp
pydisort/disort/disort_impl.h
pydisort/disort/index.h
pydisort/disort/loops.cuh
pydisort/disort/scattering_moments.cpp
pydisort/disort/scattering_moments.hpp
pydisort/disort/vectorize.cpp
pydisort/disort/vectorize.hpp
pydisort/disort/utils/DispatchStub.cpp
pydisort/lib/libdisort_release.so
pydisort-1.3.6.dist-info/METADATA
pydisort-1.3.6.dist-info/WHEEL
pydisort-1.3.6.dist-info/top_level.txt
pydisort-1.3.6.dist-info/RECORD
pydisort-1.3.6.dist-info/licenses/LICENSE
