Metadata-Version: 2.4
Name: pydisort
Version: 1.3.6
Summary: Modern Python package for DISORT with support for parallel computation.
Author-email: Zoey Hu <zoey.zyhu@gmail.com>
License-Expression: GPL-3.0-or-later
Project-URL: Repository, https://github.com/zoeyzyhu/pydisort
Project-URL: Documentation, https://pydisort.readthedocs.io/
Project-URL: Issues, https://github.com/zoeyzyhu/pydisort/issues
Keywords: DISORT,radiative transfer,astrophysics,atmospheric science
Classifier: Development Status :: 5 - Production/Stable
Classifier: Intended Audience :: Science/Research
Classifier: Intended Audience :: Developers
Classifier: Intended Audience :: Education
Classifier: Topic :: Scientific/Engineering
Classifier: Topic :: Scientific/Engineering :: Atmospheric Science
Classifier: Topic :: Scientific/Engineering :: Physics
Classifier: Programming Language :: Python :: 3
Classifier: Programming Language :: Python :: 3.9
Classifier: Programming Language :: Python :: 3.10
Classifier: Programming Language :: Python :: 3.11
Classifier: Programming Language :: Python :: 3.12
Classifier: Programming Language :: Python :: 3.13
Classifier: Operating System :: POSIX :: Linux
Classifier: Operating System :: MacOS :: MacOS X
Requires-Python: >=3.9
License-File: LICENSE
Requires-Dist: numpy
Requires-Dist: torch<=2.7.1,>=2.7.0
Dynamic: license-file
